{
  "region": "cambridge",
  "model_type": "logistic",
  "validation_method": "spatial_block_cv",
  "n_blocks": 9,
  "thinning_resolution_deg": 0.005,
  "negative_ratio": 5,
  "base_seed": 42,
  "species": [
    {
      "species": "Quercus robur",
      "n_occurrences_raw": 123,
      "n_occurrences_thinned": 44,
      "n_valid_folds": 9,
      "auc_mean": 0.6626493895180763,
      "auc_std": 0.18857254074792915,
      "auc_vs_random": 0.16933099570338625,
      "f1_mean": 0.36985541691424045,
      "precision_mean": 0.6111111111111112,
      "recall_mean": 0.2994388327721661,
      "optimal_threshold": 0.19444444444444445
    },
    {
      "species": "Fraxinus excelsior",
      "n_occurrences_raw": 428,
      "n_occurrences_thinned": 86,
      "n_valid_folds": 9,
      "auc_mean": 0.6210644663300342,
      "auc_std": 0.13548917005482236,
      "auc_vs_random": 0.12444012864679066,
      "f1_mean": 0.5472380923361315,
      "precision_mean": 0.6395265228598562,
      "recall_mean": 0.5055759055759056,
      "optimal_threshold": 0.11666666666666667
    },
    {
      "species": "Urtica dioica",
      "n_occurrences_raw": 635,
      "n_occurrences_thinned": 109,
      "n_valid_folds": 9,
      "auc_mean": 0.6285723541980306,
      "auc_std": 0.1587474081072101,
      "auc_vs_random": 0.13705190333881484,
      "f1_mean": 0.6018088097371985,
      "precision_mean": 0.6982323232323232,
      "recall_mean": 0.5558321308321309,
      "optimal_threshold": 0.17777777777777778
    },
    {
      "species": "Alnus glutinosa",
      "n_occurrences_raw": 70,
      "n_occurrences_thinned": 33,
      "n_valid_folds": 6,
      "auc_mean": 0.4854702326293236,
      "auc_std": 0.20228487042155263,
      "auc_vs_random": -0.006963479491888626,
      "f1_mean": 0.3183982683982684,
      "precision_mean": 0.49999999999999994,
      "recall_mean": 0.288510101010101,
      "optimal_threshold": 0.16666666666666666
    },
    {
      "species": "Salix caprea",
      "n_occurrences_raw": 47,
      "n_occurrences_thinned": 20,
      "n_valid_folds": 7,
      "auc_mean": 0.7876984126984128,
      "auc_std": 0.21956675887396693,
      "auc_vs_random": 0.2731150793650793,
      "f1_mean": 0.6938775510204083,
      "precision_mean": 0.75,
      "recall_mean": 0.6785714285714286,
      "optimal_threshold": 0.10714285714285714
    }
  ]
}